MANIFEST.in
README.rst
setup.py
json_pointer/__init__.py
json_pointer/pointer.py
json_pointer/test.py
json_pointer.egg-info/PKG-INFO
json_pointer.egg-info/SOURCES.txt
json_pointer.egg-info/dependency_links.txt
json_pointer.egg-info/top_level.txt