Metadata-Version: 1.0
Name: json-pointer
Version: 0.1.2
Summary: Simple implementation of the json-pointer spec
Home-page: UNKNOWN
Author: Ernst Odolphi
Author-email: ernst.odolphi@sanomamedia.nl
License: Copyright Sanoma Media
Platform: UNKNOWN
